<?xml version="1.0" encoding="UTF-8" standalone="no"?>
<featureModel>
	<properties />
	<struct>
		<and abstract="true" mandatory="true" name="Arith">
			<feature mandatory="true" name="Base" />
			<feature name="Bool" />
			<feature name="BoolBinOp" />
			<feature name="BinOp" />
			<feature name="BoolUnOp" />
			<feature name="UnOp" />
			<feature name="Let" />
			<feature name="BinOp_Vars" />
			<feature name="UnOp_Vars" />
			<feature name="ITE" />
			<feature name="ITE_Vars" />
			<feature name="Lambda" />
			<feature name="CmdLine" />
			<feature name="Vars" />
		</and>
	</struct>
	<constraints />
	<calculations Auto="true" Constraints="true" Features="true"
		Redundant="true" Tautology="true" />
	<comments />
	<featureOrder userDefined="false" />
</featureModel>
