<?xml version="1.0" encoding="UTF-8" standalone="no"?>
	<featureModel>
		<struct>
			<and abstract="true" mandatory="true" name="ExpressionProductLine">
				<and abstract="true" mandatory="true" name="Operations">
					<feature abstract="true" mandatory="true" name="Kore"/>
					<feature abstract="true" name="Print"/>
					<feature abstract="true" name="Eval"/>
				</and>
				<and abstract="true" mandatory="true" name="Structs">
					<feature abstract="true" mandatory="true" name="Core"/>
					<feature abstract="true" mandatory="true" name="Num"/>
					<feature abstract="true" name="Neg"/>
					<feature abstract="true" name="Plus"/>
				</and>
				<and abstract="true" hidden="true" mandatory="true" name="Derivatives">
					<feature mandatory="true" name="CK"/>
					<feature name="CE"/>
					<feature name="CP"/>
					<feature mandatory="true" name="BK"/>
					<feature name="BE"/>
					<feature name="BP"/>
					<feature name="NK"/>
					<feature name="NE"/>
					<feature name="NP"/>
					<feature name="PK"/>
					<feature name="PE"/>
					<feature name="PP"/>
				</and>
			</and>
		</struct>
		<constraints>
			<rule>
				<eq>
					<var>Neg</var>
					<var>NK</var>
				</eq>
			</rule>
			<rule>
				<eq>
					<var>Plus</var>
					<var>PK</var>
				</eq>
			</rule>
			<rule>
				<conj>
					<eq>
						<var>Eval</var>
						<var>CE</var>
					</eq>
					<eq>
						<var>Eval</var>
						<var>BE</var>
					</eq>
				</conj>
			</rule>
			<rule>
				<conj>
					<eq>
						<var>Print</var>
						<var>CP</var>
					</eq>
					<eq>
						<var>Print</var>
						<var>BP</var>
					</eq>
				</conj>
			</rule>
			<rule>
				<eq>
					<conj>
						<var>Neg</var>
						<var>Eval</var>
					</conj>
					<var>NE</var>
				</eq>
			</rule>
			<rule>
				<eq>
					<conj>
						<var>Neg</var>
						<var>Print</var>
					</conj>
					<var>NP</var>
				</eq>
			</rule>
			<rule>
				<eq>
					<conj>
						<var>Plus</var>
						<var>Eval</var>
					</conj>
					<var>PE</var>
				</eq>
			</rule>
			<rule>
				<eq>
					<conj>
						<var>Plus</var>
						<var>Print</var>
					</conj>
					<var>PP</var>
				</eq>
			</rule>
		</constraints>
		<comments>
			<c>Ops { eqn }</c>
			<c>Structs { eqn }</c>
		</comments>
	</featureModel>
